[
    {
        "CopyId": 1151,
        "Name": "天通苑东站",
        "Equips": [
            4018,
            4027,
            4031,
            4032
        ],
        "Heros": [
            {
                "HeroId": "1001",
                "Level": 1,
                "Floor": 1,
                "Star": 1,
                "SkillLevels": [
                    1,
                    1,
                    1,
                    1
                ]
            }
        ]
    },
    {
        "CopyId": 1152,
        "Name": "清河营站",
        "Equips": [
            4002,
            4025,
            4033,
            5013
        ],
        "Heros": [
            {
                "HeroId": "1001",
                "Level": 1,
                "Floor": 1,
                "Star": 1,
                "SkillLevels": [
                    1,
                    1,
                    1,
                    1
                ]
            }
        ]
    },
    {
        "CopyId": 1153,
        "Name": "勇士营站",
        "Equips": [
            4026,
            4003,
            4034,
            5012
        ],
        "Heros": [
            {
                "HeroId": "1001",
                "Level": 1,
                "Floor": 1,
                "Star": 1,
                "SkillLevels": [
                    1,
                    1,
                    1,
                    1
                ]
            }
        ]
    },
    {
        "CopyId": 1154,
        "Name": "望京西站",
        "Equips": [
            3011,
            4030,
            4036,
            5011
        ],
        "Heros": [
            {
                "HeroId": "1001",
                "Level": 1,
                "Floor": 1,
                "Star": 1,
                "SkillLevels": [
                    1,
                    1,
                    1,
                    1
                ]
            }
        ]
    },
    {
        "CopyId": 1155,
        "Name": "太阳宫站",
        "Equips": [
            3012,
            4023,
            4037,
            5008
        ],
        "Heros": [
            {
                "HeroId": "1001",
                "Level": 1,
                "Floor": 1,
                "Star": 1,
                "SkillLevels": [
                    1,
                    1,
                    1,
                    1
                ]
            }
        ]
    },
    {
        "CopyId": 1156,
        "Name": "西坝河站",
        "Equips": [
            4007,
            4029,
            4038,
            5010
        ],
        "Heros": [
            {
                "HeroId": "1001",
                "Level": 1,
                "Floor": 1,
                "Star": 1,
                "SkillLevels": [
                    1,
                    1,
                    1,
                    1
                ]
            }
        ]
    },
    {
        "CopyId": 2151,
        "Name": "香河园站",
        "Equips": [
            4018,
            4027,
            4031,
            4032
        ],
        "HeroParts": [
            1018
        ],
        "Heros": [
            {
                "HeroId": "1001",
                "Level": 1,
                "Floor": 1,
                "Star": 1,
                "SkillLevels": [
                    1,
                    1,
                    1,
                    1
                ]
            }
        ]
    },
    {
        "CopyId": 2152,
        "Name": "工人体育场站",
        "Equips": [
            4002,
            4025,
            4033,
            5013
        ],
        "Heros": [
            {
                "HeroId": "1001",
                "Level": 1,
                "Floor": 1,
                "Star": 1,
                "SkillLevels": [
                    1,
                    1,
                    1,
                    1
                ]
            }
        ]
    },
    {
        "CopyId": 2153,
        "Name": "东大桥站",
        "Equips": [
            4026,
            4003,
            4034,
            5012
        ],
        "HeroParts": [
            1026
        ],
        "Heros": [
            {
                "HeroId": "1001",
                "Level": 1,
                "Floor": 1,
                "Star": 1,
                "SkillLevels": [
                    1,
                    1,
                    1,
                    1
                ]
            }
        ]
    },
    {
        "CopyId": 2154,
        "Name": "永安里站",
        "Equips": [
            3011,
            4030,
            4036,
            5011
        ],
        "HeroParts": [
            1030
        ],
        "Heros": [
            {
                "HeroId": "1001",
                "Level": 1,
                "Floor": 1,
                "Star": 1,
                "SkillLevels": [
                    1,
                    1,
                    1,
                    1
                ]
            }
        ]
    },
    {
        "CopyId": 2155,
        "Name": "广渠门外站",
        "Equips": [
            3012,
            4023,
            4037,
            5008
        ],
        "HeroParts": [
            1023
        ],
        "Heros": [
            {
                "HeroId": "1001",
                "Level": 1,
                "Floor": 1,
                "Star": 1,
                "SkillLevels": [
                    1,
                    1,
                    1,
                    1
                ]
            }
        ]
    },
    {
        "CopyId": 2156,
        "Name": "潘家园西站",
        "Equips": [
            4007,
            4029,
            4038,
            5010
        ],
        "HeroParts": [
            1020
        ],
        "Heros": [
            {
                "HeroId": "1001",
                "Level": 1,
                "Floor": 1,
                "Star": 1,
                "SkillLevels": [
                    1,
                    1,
                    1,
                    1
                ]
            }
        ]
    }
]